rpkimancer_doa/__init__.py
rpkimancer_doa/communities.py
rpkimancer_doa/conjure.py
rpkimancer_doa/sigobj.py
rpkimancer_doa/asn1/RpkiDiscardOriginAttestation-2021.asn
rpkimancer_doa/asn1/__init__.py
rpkimancer_doa-0.0.2.dist-info/METADATA
rpkimancer_doa-0.0.2.dist-info/WHEEL
rpkimancer_doa-0.0.2.dist-info/entry_points.txt
rpkimancer_doa-0.0.2.dist-info/top_level.txt
rpkimancer_doa-0.0.2.dist-info/RECORD
