Metadata-Version: 2.1
Name: rpkimancer-doa
Version: 0.0.2
Summary: A rpkimancer plugin providing support for Discard Origin Authorizations
Author: Ben Maddison
Author-email: benm@workonline.africa
License: MIT
Keywords: rpki,draft-spaghetti-sidrops-rpki-doa
Platform: UNKNOWN
Classifier: License :: OSI Approved :: MIT License
Classifier: Programming Language :: Python :: 3
Classifier: Programming Language :: Python :: 3.8
Classifier: Programming Language :: Python :: 3.9
Requires-Python: >=3.8
Requires-Dist: rpkimancer (<0.2.0,>=0.1.0)
